CHANGELOG.rst
LICENSE
MANIFEST.in
README.rst
pyproject.toml
setup.cfg
setup.py
tox.ini
.circleci/config.yml
.github/workflows/publish.yml
Mopidy_RadioBrowser.egg-info/PKG-INFO
Mopidy_RadioBrowser.egg-info/SOURCES.txt
Mopidy_RadioBrowser.egg-info/dependency_links.txt
Mopidy_RadioBrowser.egg-info/entry_points.txt
Mopidy_RadioBrowser.egg-info/not-zip-safe
Mopidy_RadioBrowser.egg-info/requires.txt
Mopidy_RadioBrowser.egg-info/top_level.txt
mopidy_radiobrowser/__init__.py
mopidy_radiobrowser/backend.py
mopidy_radiobrowser/ext.conf
mopidy_radiobrowser/library.py
mopidy_radiobrowser/playback.py
mopidy_radiobrowser/radiobrowser.py
mopidy_radiobrowser/translator.py
tests/__init__.py
tests/test_extension.py
tests/test_playlists.py